base_class_package/__init__.py
base_class_package/normal_point.py
base_class_package-0.2.0.dist-info/METADATA
base_class_package-0.2.0.dist-info/WHEEL
base_class_package-0.2.0.dist-info/top_level.txt
base_class_package-0.2.0.dist-info/RECORD
