Metadata-Version: 2.1
Name: base_class_package
Version: 0.2.0
Summary: Counting normal point
Author: Nodar
Author-email: nodi3m@gmail.com
